{
  "project_info": {
    "project_number": "866408839187",
    "project_id": "smartjug-ea328"
  },
  "client": [
    {
      "client_info": {
        "mobilesdk_app_id": "1:866408839187:android:c4fcd7b5546eb413",
        "android_client_info": {
          "package_name": "com.dev.christopher.smartjug"
        }
      },
      "oauth_client": [],
      "api_key": [
        {
          "current_key": "AIzaSyB85sUSzPk1VBAwoOuGZy-ETTZKXSp46uM"
        }
      ],
      "services": {
        "analytics_service": {
          "status": 1
        },
        "appinvite_service": {
          "status": 1,
          "other_platform_oauth_client": []
        },
        "ads_service": {
          "status": 1
        }
      }
    }
  ],
  "configuration_version": "1"
}